[{"title": "IX Carreira do Entroido", "place": "Trazo", "url": "https://atletismo.gal/competicions/ix-carreira-do-entroido/?cp_date=01/03/2025", "start": "2025-03-01"}, {"title": "Xogade \u2013 Atletismo en Pista \u2013 Provincia da Coru\u00f1a 2025", "place": "", "url": "https://atletismo.gal/competicions/xogade-atletismo-pista-provincia-da-coruna-2025/?cp_date=01/03/2025", "start": "2025-03-01"}, {"title": "Xogade \u2013 Atletismo en Pista \u2013 Santiago 2025 \u2013 1\u00aa Xornada \u2013 Programa A", "place": "Pobra do Carami\u00f1al, A", "url": "https://atletismo.gal/competicions/xogade-atletismo-en-pista-santiago-2025-1a-xornada-programa-a/?cp_date=01/03/2025", "start": "2025-03-01"}, {"title": "Campionato de Espa\u00f1a de Atletismo Sub18 Short Track 2025", "place": "Valencia", "url": "https://atletismo.gal/competicions/campionato-de-espana-de-atletismo-sub18-short-track-2025/?cp_date=01/03/2025", "start": "2025-03-02"}, {"title": "Xogade \u2013 Atletismo en Pista \u2013 Coru\u00f1a 2025 \u2013 1\u00aa Xornada \u2013 Programa A", "place": "Ferrol", "url": "https://atletismo.gal/competicions/xogade-en-pista-2025-zona-coruna-ferrol-xornada-a/?cp_date=01/03/2025", "start": "2025-03-02"}, {"title": "XXXVIII Campionato de Europa Short Track", "place": "Apeldoorn (NED)", "url": "https://atletismo.gal/competicions/xxxviii-campionato-de-europa-short-track/?cp_date=01/03/2025", "start": "2025-03-06"}, {"title": "XX Campionato Xunta de Galicia de Atletismo Sub12 \u2013 XXV Sub10 en Pista Curta", "place": "Ourense", "url": "https://atletismo.gal/competicions/xx-campionato-xunta-de-galicia-de-atletismo-sub12-xxv-sub10-en-pista-curta/?cp_date=01/03/2025", "start": "2025-03-08"}, {"title": "Campionato de Espa\u00f1a de Atletismo Sub20 Short Track 2025", "place": "Salamanca", "url": "https://atletismo.gal/competicions/campionato-de-espana-de-atletismo-sub20-short-track-2025/?cp_date=01/03/2025", "start": "2025-03-08"}, {"title": "XXII Campionato Xunta de Galicia de Atletismo Sub14 en Pista Curta", "place": "Ourense", "url": "https://atletismo.gal/competicions/xxii-campionato-xunta-de-galicia-de-atletismo-sub14-en-pista-curta/?cp_date=01/03/2025", "start": "2025-03-09"}, {"title": "I Carreira Terra do Queixo. Etapa Melide \u2013 Arz\u00faa (Cami\u00f1o de Santiago)", "place": "Melide - Arz\u00faa", "url": "https://atletismo.gal/competicions/i-carreira-etapa-melide-arzua-camino-de-santiago/?cp_date=01/03/2025", "start": "2025-03-09"}, {"title": "Campionato de Espa\u00f1a de Marcha en Ruta Absoluto \u2013 M\u00e1ster (35 km) 2025", "place": "Mar\u00edn", "url": "https://atletismo.gal/competicions/campionato-de-espana-de-marcha-en-ruta-absoluto-master-35-km-2025/?cp_date=01/03/2025", "start": "2025-03-09"}, {"title": "Campionato de Espa\u00f1a Sub20 \u2013 Sub16 de Marcha por Federaci\u00f3ns Auton\u00f3micas 2025", "place": "Mar\u00edn", "url": "https://atletismo.gal/competicions/campionato-de-espana-sub20-sub16-de-marcha-por-federacions-autonomicas-2025/?cp_date=01/03/2025", "start": "2025-03-09"}, {"title": "Campionato de Espa\u00f1a de 10 km Ruta Absoluto \u2013 M\u00e1ster 2025", "place": "Bilbao", "url": "https://atletismo.gal/competicions/campionato-de-espana-de-10-km-ruta-absoluto-master-2025/?cp_date=01/03/2025", "start": "2025-03-09"}, {"title": "IV Carreira pola Igualdade Concello de Nar\u00f3n", "place": "Nar\u00f3n", "url": "https://atletismo.gal/competicions/iv-carreira-pola-igualdade-concello-de-naron/?cp_date=01/03/2025", "start": "2025-03-09"}, {"title": "XIII Carreira Pedestre Concello de Camari\u00f1as", "place": "Camari\u00f1as", "url": "https://atletismo.gal/competicions/xiii-carreira-pedestre-concello-de-camarinas/?cp_date=01/03/2025", "start": "2025-03-09"}, {"title": "Campionato de Espa\u00f1a de Atletismo Sub16 Short Track 2025", "place": "Ourense", "url": "https://atletismo.gal/competicions/campionato-de-espana-de-atletismo-sub16-short-track-2025/?cp_date=01/03/2025", "start": "2025-03-15"}, {"title": "Copa de Europa de Lanzamentos 2025", "place": "Nicosia (CYP)", "url": "https://atletismo.gal/competicions/copa-de-europa-de-lanzamentos-2025/?cp_date=01/03/2025", "start": "2025-03-15"}, {"title": "XIII Carreira Popular Torre de Hercules 2024", "place": "Coru\u00f1a, A", "url": "https://atletismo.gal/competicions/xiii-carreira-popular-torre-de-hercules-2024/?cp_date=01/03/2025", "start": "2025-03-15"}, {"title": "II Trail Laxe dos Bolos 2025", "place": "Caldas de Reis", "url": "https://atletismo.gal/competicions/ii-trail-laxe-dos-bolos-2024/?cp_date=01/03/2025", "start": "2025-03-16"}, {"title": "X Campionato Xunta de Galicia de Trail Running Classic", "place": "Caldas de Reis", "url": "https://atletismo.gal/competicions/x-campionato-xunta-de-galicia-de-trail-running-classic/?cp_date=01/03/2025", "start": "2025-03-16"}, {"title": "Campionato de Espa\u00f1a de Marat\u00f3n \u2013 Absoluto \u2013 M\u00e1ster 2025", "place": "Barcelona", "url": "https://atletismo.gal/competicions/campionato-de-espana-de-maraton-absoluto-master-2025/?cp_date=01/03/2025", "start": "2025-03-16"}, {"title": "Campionato do Mundo Short Track 2025", "place": "Nanjing (CHN)", "url": "https://atletismo.gal/competicions/campionato-do-mundo-short-track-2025/?cp_date=01/03/2025", "start": "2025-03-21"}, {"title": "Xogade \u2013 Atletismo en Pista \u2013 Coru\u00f1a 2025 \u2013 2\u00aa Xornada \u2013 Programa B", "place": "Ferrol", "url": "https://atletismo.gal/competicions/xogade-en-pista-2025-zona-coruna-ferrol-xornada-b/?cp_date=01/03/2025", "start": "2025-03-22"}, {"title": "Xogade \u2013 Atletismo en Pista \u2013 Provincia de Ourense 2025", "place": "Ourense", "url": "https://atletismo.gal/competicions/xogade-atletismo-en-pista-provincia-de-ourense-2025/?cp_date=01/03/2025", "start": "2025-03-22"}, {"title": "Xogade \u2013 Atletismo en Pista \u2013 Programa A \u2013 Ourense 2025 \u2013 1\u00aa Xornada", "place": "Pereiro de Aguiar, O", "url": "https://atletismo.gal/competicions/xogade-atletismo-en-pista-programa-a-ourense-2025-1a-xornada/?cp_date=01/03/2025", "start": "2025-03-22"}, {"title": "II Ourense Series Provinciais de Atletismo", "place": "Ourense", "url": "https://atletismo.gal/competicions/ii-ourense-series-provinciais-de-atletismo/?cp_date=01/03/2025", "start": "2025-03-22"}, {"title": "II Ourense Series Provinciais de Atletismo \u2013 Ourense Xornada 1", "place": "Pereiro de Aguiar, O", "url": "https://atletismo.gal/competicions/ii-ourense-series-provinciais-de-atletismo-ourense-xornada-1/?cp_date=01/03/2025", "start": "2025-03-22"}, {"title": "Xogade \u2013 Atletismo en Pista \u2013 Provincia de Lugo 2025", "place": "", "url": "https://atletismo.gal/competicions/xogade-atletismo-en-pista-provincia-de-lugo-2025/?cp_date=01/03/2025", "start": "2025-03-22"}, {"title": "Xogade \u2013 Atletismo en Pista \u2013 Cervo 2025 \u2013 1\u00aa Xornada", "place": "Cervo", "url": "https://atletismo.gal/competicions/xogade-atletismo-en-pista-cervo-2025-1a-xornada/?cp_date=01/03/2025", "start": "2025-03-22"}, {"title": "II Trofeo Gus Dacal categorias menores \u2013 Concello Ponte Caldelas", "place": "Pontevedra", "url": "https://atletismo.gal/competicions/trofeo-gus-dacal-categorias-menores-concello-ponte-caldelas/?cp_date=01/03/2025", "start": "2025-03-22"}, {"title": "XVI 10 Km. Concello de O Porri\u00f1o", "place": "Porri\u00f1o, O", "url": "https://atletismo.gal/competicions/xvii-10-km-concello-de-o-porrino/?cp_date=01/03/2025", "start": "2025-03-23"}, {"title": "Campionato do Mundo M\u00e1ster Short Track 2025", "place": "Gainsville (USA)", "url": "https://atletismo.gal/competicions/campionato-do-mundo-master-short-track-2025/?cp_date=01/03/2025", "start": "2025-03-23"}, {"title": "Xogade \u2013 Atletismo en Pista \u2013 Santiago 2025 \u2013 2\u00aa Xornada \u2013 Programa B", "place": "Santiago de Compostela", "url": "https://atletismo.gal/competicions/xogade-atletismo-en-pista-santiago-2025-2a-xornada-programa-b/?cp_date=01/03/2025", "start": "2025-03-23"}, {"title": "Xogade \u2013 Atletismo en Pista \u2013 Provincia de Pontevedra 2025", "place": "", "url": "https://atletismo.gal/competicions/xogade-atletismo-en-pista-provincia-de-pontevedra-2025/?cp_date=01/03/2025", "start": "2025-03-23"}, {"title": "Xogade \u2013 Atletismo en Pista \u2013 Pontevedra 2025 \u2013 Programa A", "place": "Pontevedra", "url": "https://atletismo.gal/competicions/xogade-atletismo-en-pista-pontevedra-2025-1a-xornada/?cp_date=01/03/2025", "start": "2025-03-23"}, {"title": "Xogade \u2013 Atletismo en Pista \u2013 Lugo 2025 \u2013 1\u00aa Xornada", "place": "Lugo", "url": "https://atletismo.gal/competicions/xogade-atletismo-en-pista-lugo-2025-1a-xornada/?cp_date=01/03/2025", "start": "2025-03-23"}, {"title": "Trofeo Ib\u00e9rico de Probas Combinadas Sub20 \u2013 Sub18 Short Track ESP-POR 2025", "place": "A designar", "url": "https://atletismo.gal/competicions/trofeo-iberico-de-probas-combinadas-sub20-sub18-short-track-esp-por-2025/?cp_date=01/03/2025", "start": "2025-03-29"}, {"title": "V Cros Solidario en favor da Investigaci\u00f3n de Duchenne e Becker \u201cUnha tarde con Samuel\u201d 2024", "place": "Santiago de Compostela", "url": "https://atletismo.gal/competicions/v-cros-solidario-en-favor-da-investigacion-de-duchenne-e-becker-unha-tarde-con-samuel-2024/?cp_date=01/03/2025", "start": "2025-03-29"}, {"title": "Xogade \u2013 Atletismo en Pista \u2013 Coru\u00f1a 2025 \u2013 3\u00aa Xornada \u2013 Programa A", "place": "Ferrol", "url": "https://atletismo.gal/competicions/xogade-en-pista-2025-zona-coruna-ferrol-xornada-a-2/?cp_date=01/03/2025", "start": "2025-03-29"}, {"title": "Xogade \u2013 Atletismo en Pista \u2013 Programa B \u2013 Ourense 2025 \u2013 2\u00aa Xornada", "place": "Pereiro de Aguiar, O", "url": "https://atletismo.gal/competicions/xogade-atletismo-en-pista-programa-b-ourense-2025-2a-xornada/?cp_date=01/03/2025", "start": "2025-03-29"}, {"title": "Xogade \u2013 Atletismo en Pista \u2013 Programa A \u2013 Valdeorras 2025 \u2013 1\u00aa Xornada", "place": "Barco de Valdeorras, O", "url": "https://atletismo.gal/competicions/xogade-atletismo-en-pista-programa-a-valdeorras-2025-1a-xornada/?cp_date=01/03/2025", "start": "2025-03-29"}, {"title": "II Ourense Series Provinciais de Atletismo \u2013 Ourense Xornada 2", "place": "Pereiro de Aguiar, O", "url": "https://atletismo.gal/competicions/ii-ourense-series-provinciais-de-atletismo-ourense-xornada-2/?cp_date=01/03/2025", "start": "2025-03-29"}, {"title": "II Ourense Series Provinciais de Atletismo \u2013 Valdeorras Xornada 1", "place": "Barco de Valdeorras, O", "url": "https://atletismo.gal/competicions/ii-ourense-series-provinciais-de-atletismo-valdeorras-xornada-1/?cp_date=01/03/2025", "start": "2025-03-29"}, {"title": "Xogade \u2013 Atletismo en Pista \u2013 Vigo 2025 \u2013 Programa A", "place": "Vigo", "url": "https://atletismo.gal/competicions/xogade-atletismo-en-pista-vigo-2025-1a-xornada-programa-a/?cp_date=01/03/2025", "start": "2025-03-29"}, {"title": "IV Trail Cova da Bruxa", "place": "Muros", "url": "https://atletismo.gal/competicions/iv-trail-cova-da-bruxa/?cp_date=01/03/2025", "start": "2025-03-30"}, {"title": "Campionato de Espa\u00f1a de Marcha 20 km Absoluto \u2013 Sub23 \u2013 M\u00e1ster 2025", "place": "San Pedro del Pinatar", "url": "https://atletismo.gal/competicions/campionato-de-espana-de-marcha-20-km-absoluto-sub23-master-2025/?cp_date=01/03/2025", "start": "2025-03-30"}, {"title": "III Edici\u00f3n 10K \u201cCosta \u00c1rtabra\u201d", "place": "Coru\u00f1a, A", "url": "https://atletismo.gal/competicions/iii-edicion-10k-costa-artabra/?cp_date=01/03/2025", "start": "2025-03-30"}, {"title": "XI Carreira Pedestre Concelllo de Oroso 2025", "place": "Oroso", "url": "https://atletismo.gal/competicions/xi-carreira-pedestre-concelllo-de-oroso-2024/?cp_date=01/03/2025", "start": "2025-03-30"}, {"title": "Xogade \u2013 Atletismo en Pista \u2013 Pontevedra 2025 \u2013 Programa B", "place": "Pontevedra", "url": "https://atletismo.gal/competicions/xogade-atletismo-en-pista-pontevedra-2025-2a-xornada/?cp_date=01/03/2025", "start": "2025-03-30"}, {"title": "Xogade \u2013 Atletismo en Pista \u2013 Lugo 2025 \u2013 2\u00aa Xornada", "place": "Lugo", "url": "https://atletismo.gal/competicions/xogade-atletismo-en-pista-lugo-2025-2a-xornada/?cp_date=01/03/2025", "start": "2025-03-30"}, {"title": "III Edici\u00f3n Os 10000 peregrinos 10 K Deputaci\u00f3n da Coru\u00f1a 2025", "place": "Santiago de Compostela", "url": "https://atletismo.gal/competicions/iii-edicion-os-10000-peregrinos-10-k-deputacion-da-coruna-2025/?cp_date=01/04/2025", "start": "2025-04-05"}, {"title": "Xogade \u2013 Atletismo en Pista \u2013 Programa A \u2013 Ourense 2025 \u2013 3\u00aa Xornada", "place": "Pereiro de Aguiar, O", "url": "https://atletismo.gal/competicions/xogade-atletismo-en-pista-programa-a-ourense-2025-3a-xornada/?cp_date=01/04/2025", "start": "2025-04-05"}, {"title": "Xogade \u2013 Atletismo en Pista \u2013 Programa B \u2013 Valdeorras 2025 \u2013 2\u00aa Xornada", "place": "Barco de Valdeorras, O", "url": "https://atletismo.gal/competicions/xogade-atletismo-en-pista-programa-b-valdeorras-2025-2a-xornada/?cp_date=01/04/2025", "start": "2025-04-05"}, {"title": "II Ourense Series Provinciais de Atletismo \u2013 Ourense Xornada 3", "place": "Pereiro de Aguiar, O", "url": "https://atletismo.gal/competicions/ii-ourense-series-provinciais-de-atletismo-ourense-xornada-3/?cp_date=01/04/2025", "start": "2025-04-05"}, {"title": "II Ourense Series Provinciais de Atletismo \u2013 Valdeorras Xornada 2", "place": "Barco de Valdeorras, O", "url": "https://atletismo.gal/competicions/ii-ourense-series-provinciais-de-atletismo-valdeorras-xornada-2/?cp_date=01/04/2025", "start": "2025-04-05"}, {"title": "Xogade \u2013 Atletismo en Pista \u2013 Vigo 2025 \u2013 Programa B", "place": "Vigo", "url": "https://atletismo.gal/competicions/xogade-atletismo-en-pista-vigo-2025-2a-xornada-programa-b/?cp_date=01/04/2025", "start": "2025-04-05"}, {"title": "Xogade \u2013 Atletismo en Pista \u2013 Cervo 2025 \u2013 2\u00aa Xornada", "place": "Cervo", "url": "https://atletismo.gal/competicions/xogade-atletismo-en-pista-cervo-2025-2a-xornada/?cp_date=01/04/2025", "start": "2025-04-05"}, {"title": "V Subida a San Cidre", "place": "Toques", "url": "https://atletismo.gal/competicions/v-subida-a-san-cidre/?cp_date=01/04/2025", "start": "2025-04-06"}, {"title": "Xogade \u2013 Atletismo en Pista \u2013 Coru\u00f1a 2025 \u2013 4\u00aa Xornada \u2013 Programa B", "place": "Ferrol", "url": "https://atletismo.gal/competicions/xogade-en-pista-2025-zona-coruna-ferrol-xornada-b-2/?cp_date=01/04/2025", "start": "2025-04-06"}, {"title": "Xogade \u2013 Atletismo en Pista \u2013 Santiago 2025 \u2013 3\u00aa Xornada \u2013 Programa A", "place": "Pobra do Carami\u00f1al, A", "url": "https://atletismo.gal/competicions/xogade-atletismo-en-pista-santiago-2025-3a-xornada-programa-a/?cp_date=01/04/2025", "start": "2025-04-06"}, {"title": "Xogade \u2013 Atletismo en Pista \u2013 Lugo 2025 \u2013 3\u00aa Xornada", "place": "Lugo", "url": "https://atletismo.gal/competicions/xogade-atletismo-en-pista-lugo-2025-3a-xornada/?cp_date=01/04/2025", "start": "2025-04-06"}, {"title": "XXXVI Reconquista Trofeo Antonio Fern\u00e1ndez", "place": "Vigo", "url": "https://atletismo.gal/competicions/xxxvi-reconquista-trofeo-antonio-fernandez/?cp_date=01/04/2025", "start": "2025-04-06"}, {"title": "IX Carreira Popular de Matogrande-Circuito Coru\u00f1a Corre", "place": "A Coru\u00f1a", "url": "https://atletismo.gal/competicions/ix-carreira-popular-de-matogrande-circuito-coruna-corre/?cp_date=01/04/2025", "start": "2025-04-06"}, {"title": "I Xornada Circu\u00edto Atletismo en Pista Pontevedra 2025", "place": "Pontevedra", "url": "https://atletismo.gal/competicions/i-xornada-circuito-atletismo-en-pista-pontevedra-2025/?cp_date=01/04/2025", "start": "2025-04-09"}, {"title": "II Control Escola de Atletismo SGP \u2013 I Xornada Froiz", "place": "Pontevedra", "url": "https://atletismo.gal/competicions/ii-control-escola-de-atletismo-sgp-i-xornada-froiz/?cp_date=01/04/2025", "start": "2025-04-09"}, {"title": "Campionato de Espa\u00f1a Trail Running Absoluto e por Federaci\u00f3ns Auton\u00f3micas 2025", "place": "A designar", "url": "https://atletismo.gal/competicions/campionato-de-espana-trail-running-absoluto-e-por-federacions-autonomicas-2025/?cp_date=01/04/2025", "start": "2025-04-12"}, {"title": "Campionato de Europa de Ruta (Marat\u00f3n \u2013 Medio Marat\u00f3n \u2013 10 km) 2025", "place": "Brussels Leuven (BEL)", "url": "https://atletismo.gal/competicions/campionato-de-europa-de-ruta-maraton-medio-maraton-10-km-2025/?cp_date=01/04/2025", "start": "2025-04-12"}, {"title": "III Trofeo Santa Ux\u00eda", "place": "Pobra do Carami\u00f1al, A", "url": "https://atletismo.gal/competicions/iii-trofeo-santa-uxia/?cp_date=01/04/2025", "start": "2025-04-12"}, {"title": "Trofeo Marcha en Pista 2025 (Cervo)", "place": "Cervo", "url": "https://atletismo.gal/competicions/trofeo-marcha-en-pista-2025-cervo/?cp_date=01/04/2025", "start": "2025-04-12"}, {"title": "XIII Carrreira Pedestre Concello de Vimianzo 2025", "place": "Vimianzo", "url": "https://atletismo.gal/competicions/xiii-carrreira-pedestre-concello-de-vimianzo-2025/?cp_date=01/04/2025", "start": "2025-04-12"}, {"title": "VIII Copa de Galicia de Clubs M\u00e1ster en Pista AL", "place": "Vigo", "url": "https://atletismo.gal/competicions/viii-copa-de-galicia-de-clubs-master-en-pista-al/?cp_date=01/04/2025", "start": "2025-04-13"}, {"title": "V Clasica Gandeira Santa Comba 2025", "place": "Santa Comba", "url": "https://atletismo.gal/competicions/v-clasica-gandeira-santa-comba-2025/?cp_date=01/04/2025", "start": "2025-04-13"}, {"title": "XXIV Campionato Xunta de Galicia de 10.000 m. Absoluto \u2013 M\u00e1ster \u2013 Sub 23 \u2013 5.000 m. Sub20 \u2013 Sub18 \u2013 V Memorial Alejandro G\u00f3mez", "place": "A designar", "url": "https://atletismo.gal/competicions/xxiv-campionato-xunta-de-galicia-de-10-000-m-absoluto-master-sub-23-5-000-m-sub20-sub18-v-memorial-alejandro-gomez/?cp_date=01/04/2025", "start": "2025-04-19"}, {"title": "X Campionato Xunta de Galicia de P\u00e9ntatlon de Lanzamentos M\u00e1ster", "place": "A designar", "url": "https://atletismo.gal/competicions/x-campionato-xunta-de-galicia-de-pentatlon-de-lanzamentos-master/?cp_date=01/04/2025", "start": "2025-04-19"}, {"title": "XXV Campionato Xunta de Galicia de Probas Combinadas M\u00e1ster en Pista AL", "place": "A designar", "url": "https://atletismo.gal/competicions/xxv-campionato-xunta-de-galicia-de-probas-combinadas-master-en-pista-al/?cp_date=01/04/2025", "start": "2025-04-19"}, {"title": "Xogade \u2013 Atletismo en Pista \u2013 Pontevedra 2025 \u2013 Programa AB Alev\u00edn/Benxam\u00edn", "place": "Pontevedra", "url": "https://atletismo.gal/competicions/xogade-atletismo-en-pista-pontevedra-2025-programa-ab/?cp_date=01/04/2025", "start": "2025-04-25"}, {"title": "Campionato de Espa\u00f1a Clubs Divisi\u00f3n de Honor 2025 \u2013 1\u00aa Xornada", "place": "Varias sedes", "url": "https://atletismo.gal/competicions/campionato-de-espana-clubs-division-de-honor-2025-1a-xornada/?cp_date=01/04/2025", "start": "2025-04-26"}, {"title": "Xogade \u2013 Atletismo en Pista \u2013 Programa B \u2013 Ourense 2025 \u2013 4\u00aa Xornada", "place": "Pereiro de Aguiar, O", "url": "https://atletismo.gal/competicions/xogade-atletismo-en-pista-programa-b-ourense-2025-4a-xornada/?cp_date=01/04/2025", "start": "2025-04-26"}, {"title": "Xogade \u2013 Atletismo en Pista \u2013 Programa B \u2013 Valdeorras 2025 \u2013 3\u00aa Xornada", "place": "Barco de Valdeorras, O", "url": "https://atletismo.gal/competicions/xogade-atletismo-en-pista-programa-b-valdeorras-2025-3a-xornada/?cp_date=01/04/2025", "start": "2025-04-26"}, {"title": "II Ourense Series Provinciais de Atletismo \u2013 Ourense Xornada 4", "place": "Pereiro de Aguiar, O", "url": "https://atletismo.gal/competicions/ii-ourense-series-provinciais-de-atletismo-ourense-xornada-4/?cp_date=01/04/2025", "start": "2025-04-26"}, {"title": "II Ourense Series Provinciais de Atletismo \u2013 Valdeorras Xornada 3", "place": "Barco de Valdeorras, O", "url": "https://atletismo.gal/competicions/ii-ourense-series-provinciais-de-atletismo-valdeorras-xornada-3/?cp_date=01/04/2025", "start": "2025-04-26"}, {"title": "Xogade \u2013 Atletismo en Pista \u2013 Santiago 2025 \u2013 4\u00aa Xornada \u2013 Programa B", "place": "Pobra do Carami\u00f1al, A", "url": "https://atletismo.gal/competicions/xogade-atletismo-en-pista-santiago-2025-4a-xornada-programa-b/?cp_date=01/04/2025", "start": "2025-04-26"}, {"title": "Xogade \u2013 Atletismo en Pista \u2013 Cervo 2025 \u2013 3\u00aa Xornada", "place": "Cervo", "url": "https://atletismo.gal/competicions/xogade-atletismo-en-pista-cervo-2025-3a-xornada/?cp_date=01/04/2025", "start": "2025-04-26"}, {"title": "XII Carreira Pedestre Batalla de Cacheiras 2025", "place": "Teo", "url": "https://atletismo.gal/competicions/xii-carreira-pedestre-batalla-de-cacheiras-2025/?cp_date=01/04/2025", "start": "2025-04-27"}, {"title": "5\u00aa Popular Faro Roncudo 2025", "place": "Ponteceso", "url": "https://atletismo.gal/competicions/5a-popular-faro-roncudo-2025/?cp_date=01/04/2025", "start": "2025-04-27"}, {"title": "Xogade \u2013 Atletismo en Pista \u2013 Pontevedra/Vigo 2025 \u2013 Programa AB Infantil", "place": "Pontevedra", "url": "https://atletismo.gal/competicions/xogade-atletismo-en-pista-pontevedra-vigo-2025-programa-ab-infantil/?cp_date=01/04/2025", "start": "2025-04-27"}, {"title": "Xogade \u2013 Atletismo en Pista \u2013 Lugo 2025 \u2013 4\u00aa Xornada", "place": "Lugo", "url": "https://atletismo.gal/competicions/xogade-atletismo-en-pista-lugo-2025-4a-xornada/?cp_date=01/04/2025", "start": "2025-04-27"}, {"title": "Carreira do Vinte\u00fan 2025", "place": "Ourense", "url": "https://atletismo.gal/competicions/carreira-do-vinteun-2025/?cp_date=01/04/2025", "start": "2025-04-27"}, {"title": "X Carreira Pedestre Popular Concello de Frades 2025", "place": "Frades", "url": "https://atletismo.gal/competicions/x-carreira-pedestre-popular-concello-de-frades-2025/?cp_date=01/05/2025", "start": "2025-05-01"}, {"title": "XI Campionato Xunta de Galicia de Clubs de Probas Combinadas \u2013 Criterium de Combinadas", "place": "A designar", "url": "https://atletismo.gal/competicions/xii-campionato-xunta-de-galicia-de-clubs-de-probas-combinadas-criterium-de-combinadas/?cp_date=01/05/2025", "start": "2025-05-03"}, {"title": "I Carreira Poular da Ba\u00f1a", "place": "Ba\u00f1a, A", "url": "https://atletismo.gal/competicions/i-carreira-poular-da-bana/?cp_date=01/05/2025", "start": "2025-05-04"}, {"title": "III Trofeo La Mochila del Deporte \u2013 Memorial Jos\u00e9 Luis Gonz\u00e1lez \u201cEdu\u201d", "place": "A Coru\u00f1a", "url": "https://atletismo.gal/competicions/iii-trofeo-la-mochila-del-deporte-memorial-jose-luis-gomez-edu/?cp_date=01/05/2025", "start": "2025-05-09"}, {"title": "Xogade \u2013 Atletismo en Pista \u2013 Vigo 2025 \u2013 Programa AB Alev\u00edn/Benxam\u00edn", "place": "Vigo", "url": "https://atletismo.gal/competicions/xogade-atletismo-en-pista-vigo-2025-programa-ab-alevin-benxamin/?cp_date=01/05/2025", "start": "2025-05-09"}, {"title": "Campionato de Espa\u00f1a de Probas Combinadas M\u00e1ster 2025", "place": "A designar", "url": "https://atletismo.gal/competicions/campionato-de-espana-de-probas-combinadas-master-2025/?cp_date=01/05/2025", "start": "2025-05-10"}, {"title": "Campionato de Espa\u00f1a Absoluto \u2013 M\u00e1ster Ultra Trail Running 2025", "place": "Azpeitia", "url": "https://atletismo.gal/competicions/campionato-de-espana-absoluto-master-ultra-trail-running-2025/?cp_date=01/05/2025", "start": "2025-05-10"}, {"title": "Campionato de Espa\u00f1a Pentatl\u00f3n Lanzamentos M\u00e1ster 2025", "place": "A designar", "url": "https://atletismo.gal/competicions/campionato-de-espana-pentatlon-lanzamentos-master-2025/?cp_date=01/05/2025", "start": "2025-05-10"}, {"title": "Campionato de Espa\u00f1a 10.000 m. Absoluto \u2013 Sub-23 2025", "place": "Mah\u00f3n", "url": "https://atletismo.gal/competicions/campionato-de-espana-10-000-m-absoluto-sub-23-2025/?cp_date=01/05/2025", "start": "2025-05-10"}, {"title": "Campionato de Espa\u00f1a 5.000 m. Sub20 \u2013 Sub18 2025", "place": "Mah\u00f3n", "url": "https://atletismo.gal/competicions/campionato-de-espana-5-000-m-sub20-sub18-2025/?cp_date=01/05/2025", "start": "2025-05-10"}, {"title": "Campionato de Espa\u00f1a de 10.000 m. \u2013 Milla M\u00e1ster 2025", "place": "A designar", "url": "https://atletismo.gal/competicions/campionato-de-espana-de-10-000-m-milla-master-2025/?cp_date=01/05/2025", "start": "2025-05-10"}, {"title": "World Athletics Relays 2025", "place": "Guangzhou (CHN)", "url": "https://atletismo.gal/competicions/world-athletics-relays-2025/?cp_date=01/05/2025", "start": "2025-05-10"}, {"title": "IX Carreira SantYago 10 Km", "place": "Santiago de Compostela", "url": "https://atletismo.gal/competicions/ix-carreira-santyago-10-km/?cp_date=01/05/2025", "start": "2025-05-10"}, {"title": "Asemblea Xeral Ordinaria FGA 2025", "place": "Santiago de Compostela", "url": "https://atletismo.gal/competicions/asemblea-xeral-ordinaria-fga-2025/?cp_date=01/05/2025", "start": "2025-05-10"}, {"title": "Xogade \u2013 Atletismo en Pista \u2013 Programa A \u2013 Valdeorras 2025 \u2013 4\u00aa Xornada", "place": "Barco de Valdeorras, O", "url": "https://atletismo.gal/competicions/xogade-atletismo-en-pista-programa-a-valdeorras-2025-4a-xornada/?cp_date=01/05/2025", "start": "2025-05-10"}, {"title": "II Ourense Series Provinciais de Atletismo \u2013 Valdeorras Xornada 4", "place": "Barco de Valdeorras, O", "url": "https://atletismo.gal/competicions/ii-ourense-series-provinciais-de-atletismo-valdeorras-xornada-4/?cp_date=01/05/2025", "start": "2025-05-10"}, {"title": "Xogade \u2013 Atletismo en Pista \u2013 Provincial Pontevedra 2025 \u2013 Infantil", "place": "Pontevedra", "url": "https://atletismo.gal/competicions/xogade-atletismo-en-pista-provincial-pontevedra-2025-infantil/?cp_date=01/05/2025", "start": "2025-05-10"}, {"title": "Xogade \u2013 Atletismo en Pista \u2013 Provincial da Coru\u00f1a 2025", "place": "Ferrol", "url": "https://atletismo.gal/competicions/xogade-atletismo-en-pista-provincial-da-coruna-2025/?cp_date=01/05/2025", "start": "2025-05-10"}, {"title": "XXXVII Copa de Galicia de Clubs Absoluta en Pista AL", "place": "A designar", "url": "https://atletismo.gal/competicions/xxxvii-copa-de-galicia-de-clubs-absoluta-en-pista-al/?cp_date=01/05/2025", "start": "2025-05-11"}, {"title": "XI Trail e Andaina Vial de Cuntis", "place": "Cuntis", "url": "https://atletismo.gal/competicions/xi-trail-e-andaina-vial-de-cuntis/?cp_date=01/05/2025", "start": "2025-05-11"}, {"title": "Xogade \u2013 Atletismo en Pista \u2013 Cervo 2025 \u2013 4\u00aa Xornada", "place": "Cervo", "url": "https://atletismo.gal/competicions/xogade-atletismo-en-pista-cervo-2025-4a-xornada/?cp_date=01/05/2025", "start": "2025-05-11"}, {"title": "XVI Carreira Popular Cross de San Pedro -Circuito Coru\u00f1a Corre", "place": "A Coru\u00f1a", "url": "https://atletismo.gal/competicions/xvi-carreira-popular-cross-de-san-pedro-circuito-coruna-corre/?cp_date=01/05/2025", "start": "2025-05-11"}, {"title": "XXXIII Campionato Xunta de Galicia de Clubs Sub16", "place": "A designar", "url": "https://atletismo.gal/competicions/xxxiii-campionato-xunta-de-galicia-de-clubs-sub16/?cp_date=01/05/2025", "start": "2025-05-17"}, {"title": "XI Carreira Cami\u00f1o das Letras 2025", "place": "Santiago de Compostela", "url": "https://atletismo.gal/competicions/xi-carreira-camino-das-letras-2025/?cp_date=01/05/2025", "start": "2025-05-17"}, {"title": "Serie Municipal \u2013 Concello de Vigo \u2013 2025", "place": "Vigo", "url": "https://atletismo.gal/competicions/serie-municipal-concello-de-vigo-2025/?cp_date=01/05/2025", "start": "2025-05-17"}, {"title": "1\u00aa Xornada Serie Municipal 2025", "place": "Vigo", "url": "https://atletismo.gal/competicions/1a-xornada-serie-municipal-2025/?cp_date=01/05/2025", "start": "2025-05-17"}, {"title": "XXXIII Campionato Xunta de Galicia de Clubs Sub20", "place": "A designar", "url": "https://atletismo.gal/competicions/xxxiii-campionato-xunta-de-galicia-de-clubs-sub20/?cp_date=01/05/2025", "start": "2025-05-18"}, {"title": "Xogade \u2013 Atletismo en Pista \u2013 Provincial Pontevedra 2025 \u2013 Alev\u00edn", "place": "Estrada, A", "url": "https://atletismo.gal/competicions/xogade-atletismo-en-pista-provincial-pontevedra-2025-alevin/?cp_date=01/05/2025", "start": "2025-05-18"}, {"title": "Trail Serra do Barbanza \u2013 2025", "place": "Pobra do Carami\u00f1al, A", "url": "https://atletismo.gal/competicions/trail-serra-do-barbanza-2025/?cp_date=01/05/2025", "start": "2025-05-18"}, {"title": "XXXIII Campionato Xunta de Galicia Sub12 \u2013 XVI Sub10 en Pista AL", "place": "A designar", "url": "https://atletismo.gal/competicions/xxxiii-campionato-xunta-de-galicia-sub12-xvi-sub10-en-pista-al/?cp_date=01/05/2025", "start": "2025-05-24"}, {"title": "Campionato de Espa\u00f1a de Clubs Divisi\u00f3n de Honor 2025 \u2013 2\u00aa Xornada", "place": "Varias sedes", "url": "https://atletismo.gal/competicions/campionato-de-espana-de-clubs-division-de-honor-2025-2a-xornada/?cp_date=01/05/2025", "start": "2025-05-24"}, {"title": "Campionato de Espa\u00f1a de Clubs Primeira Divisi\u00f3n 2025 \u2013 2\u00aa Xornada", "place": "Varias sedes", "url": "https://atletismo.gal/competicions/campionato-de-espana-de-clubs-primeira-division-2025-2a-xornada/?cp_date=01/05/2025", "start": "2025-05-24"}, {"title": "XVIII Copa de Europa de 10.000 m", "place": "Pace", "url": "https://atletismo.gal/competicions/xviii-copa-de-europa-de-10-000-m/?cp_date=01/05/2025", "start": "2025-05-24"}, {"title": "IX Carreira Pedestre Concello de Dumbria 2025", "place": "Dumbr\u00eda", "url": "https://atletismo.gal/competicions/ix-carreira-pedestre-concello-de-dumbria-2025/?cp_date=01/05/2025", "start": "2025-05-24"}, {"title": "Carreira do Couto 2025", "place": "Ourense", "url": "https://atletismo.gal/competicions/carreira-do-couto-2025/?cp_date=01/05/2025", "start": "2025-05-24"}, {"title": "XXVIII Carreira Popular Concello de Ordes 2025", "place": "Ordes", "url": "https://atletismo.gal/competicions/xxviii-carreira-popular-concello-de-ordes-2025/?cp_date=01/05/2025", "start": "2025-05-24"}, {"title": "I Campionato Xunta de Galicia de Trail Running por Clubs", "place": "Barbad\u00e1s", "url": "https://atletismo.gal/competicions/i-campionato-xunta-de-galicia-de-trail-running-por-clubs/?cp_date=01/05/2025", "start": "2025-05-25"}, {"title": "Campionato de Europa M\u00e1ster Off Road 2025", "place": "Nicolosi (ITA)", "url": "https://atletismo.gal/competicions/campionato-de-europa-master-off-road-2025/?cp_date=01/05/2025", "start": "2025-05-29"}, {"title": "Campionato Xunta de Galicia de Probas Combinadas Sub23 \u2013 Sub20 \u2013 Sub16 en Pista AL 2025", "place": "A designar", "url": "https://atletismo.gal/competicions/campionato-xunta-de-galicia-de-probas-combinadas-sub23-sub20-sub16-en-pista-al-2025/?cp_date=01/05/2025", "start": "2025-05-31"}, {"title": "XXX Campionato Xunta de Galicia de Atletismo Sub18 en Pista AL", "place": "A designar", "url": "https://atletismo.gal/competicions/xxx-campionato-xunta-de-galicia-de-atletismo-sub18-en-pista-al/?cp_date=01/05/2025", "start": "2025-05-31"}, {"title": "Campionato de Espa\u00f1a de Federaci\u00f3ns Auton\u00f3micas Probas Combinadas 2025", "place": "Fuerteventura", "url": "https://atletismo.gal/competicions/campionato-de-espana-de-federacions-autonomicas-probas-combinadas-2025/?cp_date=01/05/2025", "start": "2025-05-31"}, {"title": "Xogade \u2013 Atletismo en Pista \u2013 Ourense 2025 \u2013 Final Provincial", "place": "Pereiro de Aguiar, O", "url": "https://atletismo.gal/competicions/xogade-atletismo-en-pista-ourense-2025-final-provincial/?cp_date=01/05/2025", "start": "2025-05-31"}, {"title": "Xogade \u2013 Atletismo en Pista \u2013 Provincial Pontevedra 2025 \u2013 Benxam\u00edn", "place": "Vigo", "url": "https://atletismo.gal/competicions/xogade-atletismo-en-pista-provincial-pontevedra-2025-benxamin/?cp_date=01/05/2025", "start": "2025-05-31"}, {"title": "2\u00aa Xornada Serie Municipal 2025", "place": "Vigo", "url": "https://atletismo.gal/competicions/2a-xornada-serie-municipal-2025/?cp_date=01/05/2025", "start": "2025-05-31"}]